stratis_cli/__init__.py
stratis_cli/_constants.py
stratis_cli/_error_codes.py
stratis_cli/_error_reporting.py
stratis_cli/_errors.py
stratis_cli/_exit.py
stratis_cli/_main.py
stratis_cli/_stratisd_constants.py
stratis_cli/_version.py
stratis_cli/_actions/__init__.py
stratis_cli/_actions/_bind.py
stratis_cli/_actions/_connection.py
stratis_cli/_actions/_constants.py
stratis_cli/_actions/_data.py
stratis_cli/_actions/_debug.py
stratis_cli/_actions/_environment.py
stratis_cli/_actions/_formatting.py
stratis_cli/_actions/_introspect.py
stratis_cli/_actions/_list_filesystem.py
stratis_cli/_actions/_list_pool.py
stratis_cli/_actions/_logical.py
stratis_cli/_actions/_physical.py
stratis_cli/_actions/_pool.py
stratis_cli/_actions/_stratis.py
stratis_cli/_actions/_stratisd_version.py
stratis_cli/_actions/_top.py
stratis_cli/_actions/_utils.py
stratis_cli/_parser/__init__.py
stratis_cli/_parser/_debug.py
stratis_cli/_parser/_encryption.py
stratis_cli/_parser/_key.py
stratis_cli/_parser/_logical.py
stratis_cli/_parser/_parser.py
stratis_cli/_parser/_physical.py
stratis_cli/_parser/_pool.py
stratis_cli/_parser/_shared.py
stratis_cli-3.8.2.data/scripts/stratis
stratis_cli-3.8.2.dist-info/licenses/LICENSE
stratis_cli-3.8.2.dist-info/METADATA
stratis_cli-3.8.2.dist-info/WHEEL
stratis_cli-3.8.2.dist-info/top_level.txt
stratis_cli-3.8.2.dist-info/RECORD
