Metadata-Version: 2.4
Name: stratis-cli
Version: 3.8.2
Summary: Stratis CLI
Home-page: https://github.com/stratis-storage/stratis-cli
Author: Anne Mulhern
Author-email: amulhern@redhat.com
License: Apache-2.0
Platform: Linux
Classifier: Development Status :: 5 - Production/Stable
Classifier: Environment :: Console
Classifier: Intended Audience :: Developers
Classifier: Intended Audience :: System Administrators
Classifier: Operating System :: POSIX :: Linux
Classifier: Programming Language :: Python
Classifier: Programming Language :: Python :: 3
Classifier: Programming Language :: Python :: Implementation :: CPython
Classifier: Topic :: System :: Filesystems
Classifier: Topic :: System :: Systems Administration
Requires-Python: >=3.9
License-File: LICENSE
Requires-Dist: dbus-client-gen>=0.4
Requires-Dist: dbus-python-client-gen>=0.7
Requires-Dist: justbytes>=0.14
Requires-Dist: packaging
Requires-Dist: psutil
Requires-Dist: python-dateutil
Requires-Dist: wcwidth
Dynamic: license-file
